picogo/ATemplate.py
picogo/Battery.py
picogo/BatteryTest.py
picogo/BlueTooth.py
picogo/BootselButton.py
picogo/BuzzerTest.py
picogo/CurrentTime.py
picogo/FirmwareVersion.py
picogo/HelloWorld.py
picogo/I2CScan.py
picogo/IRObstacleAvoidance.py
picogo/IRSensor.py
picogo/LCD.py
picogo/LCDBatteryTest.py
picogo/LCDGraphicTest.py
picogo/LCDImageTest.py
picogo/LCDPrintTest.py
picogo/LCDTextTest.py
picogo/LCDUltraSonicTest.py
picogo/LEDBlink.py
picogo/LEDBlinkTimer.py
picogo/LineTracking.py
picogo/LineTracking2.py
picogo/LineTrackingNormal.py
picogo/LineTrackingOld.py
picogo/LineTrackingPID.py
picogo/LogoText.py
picogo/LogoText_01.py
picogo/MainFileCopy.py
picogo/Motor.py
picogo/MotorStop.py
picogo/MotorTest.py
picogo/Motor_org.py
picogo/ObstacleAvoidance - old.py
picogo/ObstacleAvoidance.py
picogo/RGBLed.py
picogo/RemoteController.py
picogo/Robot.py
picogo/TRSensor.py
picogo/TRSensorTest.py
picogo/TextNumber.py
picogo/UltraSonic.py
picogo/UltraSonicInfraredFollow.py
picogo/UltraSonicInfraredObstacleAvoidance.py
picogo/UltraSonicObstacleAvoidance.py
picogo/UltraSonicTest.py
picogo/__init__.py
picogo/main.py
picogo/mainFile.py
picogo/picozero.py
picogo-0.0.25.dist-info/LICENSE.md
picogo-0.0.25.dist-info/METADATA
picogo-0.0.25.dist-info/WHEEL
picogo-0.0.25.dist-info/top_level.txt
picogo-0.0.25.dist-info/RECORD
